directplot/__init__.py
directplot/__main__.py
directplot/directplot.py
directplot-0.5.2.dist-info/LICENSE
directplot-0.5.2.dist-info/METADATA
directplot-0.5.2.dist-info/WHEEL
directplot-0.5.2.dist-info/top_level.txt
directplot-0.5.2.dist-info/RECORD
