Metadata-Version: 2.1
Name: directplot
Version: 0.5.2
Summary: Educational library to directly plot single data points
Home-page: https://github.com/GeorgBraun/python-directplot
Author: GeorgBraun
Author-email: georg.braun@hm.edu
License: MIT License
Project-URL: Bug Tracker, https://github.com/GeorgBraun/python-directplot/issues
Classifier: Programming Language :: Python :: 3
Classifier: License :: OSI Approved :: MIT License
Classifier: Operating System :: OS Independent
Requires-Python: >=3.6
License-File: LICENSE
Requires-Dist: matplotlib (>=3.3.4)
